MANIFEST.in
README.md
setup.cfg
setup.py
django_stats2/__init__.py
django_stats2/apps.py
django_stats2/fields.py
django_stats2/mixins.py
django_stats2/models.py
django_stats2/objects.py
django_stats2/settings.py
django_stats2.egg-info/PKG-INFO
django_stats2.egg-info/SOURCES.txt
django_stats2.egg-info/dependency_links.txt
django_stats2.egg-info/top_level.txt
django_stats2/migrations/0001_initial.py
django_stats2/migrations/0002_auto_20161025_1156.py
django_stats2/migrations/__init__.py