Metadata-Version: 1.1
Name: django-stats2
Version: 0.2.3
Summary: Easily create stats for your models
Home-page: https://github.com/fmartingr/django-stats2
Author: Felipe Martin
Author-email: me@fmartingr.com
License: UNKNOWN
Download-URL: https://github.com/fmartingr/django-stats2/tarball/0.2.3
Keywords: django,stats
Platform: UNKNOWN
